{"about_index.md":"977ba16f","articles_index.md":"78afffd0","articles_what-is-service-reliability.md":"59997285","documentation_conventions.md":"955767d6","documentation_discuss.md":"18985003","documentation_goals.md":"53f3e470","documentation_index.md":"ac5ddad7","documentation_monitoring.md":"12bd9b13","documentation_observability.md":"16522521","documentation_rationale.md":"33d57ff3","documentation_service-modifier.md":"56d79ce1","documentation_service-reliability.md":"5c6d1ece","documentation_service-state.md":"e1cc076b","documentation_service-variable.md":"58a75752","documentation_service.md":"2bf70f01","documentation_thesis.md":"f0179f64","index.md":"157a7a96"}
